dancingbot_python/__init__.py
dancingbot_python/dancingbot_header.py
dancingbot_python/header.py
dancingbot_python-0.6.dist-info/METADATA
dancingbot_python-0.6.dist-info/WHEEL
dancingbot_python-0.6.dist-info/top_level.txt
dancingbot_python-0.6.dist-info/RECORD
